<annotation>
  <folder>toyota</folder>
  <filename>Toyota24</filename>
  <path>C:\Users\MELISSA\Desktop\cars1\images\train\toyota\Toyota24.jpg</path>
  <source>
    <database>Unknown</database>
  </source>
  <size>
    <width>303</width>
    <height>166</height>
    <depth>3</depth>
  </size>
  <segmented>0</segmented>
  <object>
    <name>Toyota</name>
    <pose>Unspecified</pose>
    <truncated>0</truncated>
    <difficult>0</difficult>
    <bndbox>
      <xmin>23</xmin>
      <ymin>22</ymin>
      <xmax>272</xmax>
      <ymax>132</ymax>
    </bndbox>
  </object>
</annotation>
